whatamithinking/services/__init__.py
whatamithinking/services/_base.py
whatamithinking/services/_windows.py
whatamithinking_services-1.1.2.dist-info/METADATA
whatamithinking_services-1.1.2.dist-info/WHEEL
whatamithinking_services-1.1.2.dist-info/RECORD
