Metadata-Version: 2.4
Name: whatamithinking-services
Version: 1.1.2
Summary: cross platform service or daemon framework
Project-URL: Homepage, https://github.com/whatamithinking/services
Project-URL: Documentation, https://github.com/whatamithinking/services
Project-URL: Repository, https://github.com/whatamithinking/services
Project-URL: Issues, https://github.com/whatamithinking/services/issues
Author-email: connormaynes@gmail.com
Keywords: daemon,service
Requires-Python: >=3.11
Requires-Dist: pywin32; platform_system == 'Windows'
Provides-Extra: dev
Requires-Dist: black; extra == 'dev'
Provides-Extra: test
